{
  "brk-doc-card": {
    "image-border-radius": {
      "value": "{brk-opt-border-radius.16}",
      "type": "borderRadius",
      "description": "NOTE : token de documentation, uniquement pour les designers."
    }
  },
  "brk-card-hero": {
    "sm": {
      "pretitle": {
        "value": {
          "fontFamily": "{brk-opt-font-family.webfont}",
          "fontWeight": "{brk-opt-font-weight.700}",
          "lineHeight": "{brk-opt-font-size.16}",
          "fontSize": "{brk-opt-font-size.16}",
          "letterSpacing": "{brk-opt-letter-spacing.0%}",
          "paragraphSpacing": "",
          "textCase": "{brk-opt-text-transform.none}",
          "textDecoration": "{brk-opt-text-decoration.none}"
        },
        "type": "typography",
        "description": "NOTE : pour le pré-titre de la carte héros, il faut toujours utiliser le token \"font-size\" pour le \"line-height\". Ceci est important surtout pour les cas dans lesquels on n'aura pas de sous-titre, car cela permet de réserver cet espace du côté code. À noter que même si cette option n'est pas disponible dans le menu déroulant, on peut copier et coller l'information d'une caisse à l'autre."
      },
      "image-height": {
        "value": "{brk-opt-sizing.32}*10",
        "type": "sizing",
        "description": " "
      },
      "padding-horizontal": {
        "value": "{brk-opt-spacing.16}",
        "type": "spacing",
        "description": " "
      },
      "padding-vertical": {
        "value": "{brk-opt-spacing.16}",
        "type": "spacing",
        "description": " "
      },
      "heading-margin-vertical": {
        "value": "{brk-opt-spacing.4}",
        "type": "spacing",
        "description": " "
      },
      "content-gap": {
        "value": "{brk-opt-spacing.16}",
        "type": "spacing",
        "description": "NOTE: Séparation minimale entre les textes et le bouton de la carte en petit format."
      },
      "heading": {
        "value": {
          "fontFamily": "{brk-opt-font-family.brand-main}",
          "fontWeight": "{brk-opt-font-weight.950}",
          "lineHeight": "{brk-opt-line-height.100%}",
          "fontSize": "{brk-opt-font-size.24}",
          "letterSpacing": "{brk-opt-letter-spacing.-2%}",
          "paragraphSpacing": "",
          "textCase": "{brk-opt-text-transform.none}",
          "textDecoration": "{brk-opt-text-decoration.none}"
        },
        "type": "typography",
        "description": " "
      },
      "body": {
        "value": {
          "fontFamily": "{brk-opt-font-family.webfont}",
          "fontWeight": "{brk-opt-font-weight.400}",
          "lineHeight": "{brk-opt-line-height.100%}",
          "fontSize": "{brk-opt-font-size.16}",
          "letterSpacing": "{brk-opt-letter-spacing.2%}",
          "paragraphSpacing": "",
          "textCase": "{brk-opt-text-transform.none}",
          "textDecoration": "{brk-opt-text-decoration.none}"
        },
        "type": "typography",
        "description": " "
      }
    },
    "md": {
      "pretitle": {
        "value": {
          "fontFamily": "{brk-opt-font-family.webfont}",
          "fontWeight": "{brk-opt-font-weight.700}",
          "lineHeight": "{brk-opt-font-size.24}",
          "fontSize": "{brk-opt-font-size.24}",
          "letterSpacing": "{brk-opt-letter-spacing.-2%}",
          "paragraphSpacing": "",
          "textCase": "{brk-opt-text-transform.none}",
          "textDecoration": "{brk-opt-text-decoration.none}"
        },
        "type": "typography",
        "description": "NOTE : pour le pré-titre de la carte héros, il faut toujours utiliser le token \"font-size\" pour le \"line-height\". Ceci est important surtout pour les cas dans lesquels on n'aura pas de sous-titre, car cela permet de réserver cet espace du côté code. À noter que même si cette option n'est pas disponible dans le menu déroulant, on peut copier et coller l'information d'une caisse à l'autre."
      },
      "image-height": {
        "value": "{brk-card-hero.sm.image-height}*1.5",
        "type": "sizing",
        "description": " "
      },
      "padding-horizontal": {
        "value": "{brk-opt-spacing.24}",
        "type": "spacing",
        "description": " "
      },
      "padding-vertical": {
        "value": "{brk-opt-spacing.24}",
        "type": "spacing",
        "description": " "
      },
      "heading-margin-vertical": {
        "value": "{brk-opt-spacing.8}",
        "type": "spacing",
        "description": " "
      },
      "content-gap": {
        "value": "{brk-opt-spacing.24}",
        "type": "spacing",
        "description": "NOTE: Séparation minimale entre les textes et le bouton de la carte en format moyen."
      },
      "heading": {
        "value": {
          "fontFamily": "{brk-opt-font-family.brand-main}",
          "fontWeight": "{brk-opt-font-weight.950}",
          "lineHeight": "{brk-opt-line-height.100%}",
          "fontSize": "{brk-opt-font-size.32}",
          "letterSpacing": "{brk-opt-letter-spacing.-2%}",
          "paragraphSpacing": "",
          "textCase": "{brk-opt-text-transform.none}",
          "textDecoration": "{brk-opt-text-decoration.none}"
        },
        "type": "typography",
        "description": " "
      },
      "body": {
        "value": {
          "fontFamily": "{brk-opt-font-family.webfont}",
          "fontWeight": "{brk-opt-font-weight.400}",
          "lineHeight": "{brk-opt-line-height.100%}",
          "fontSize": "{brk-opt-font-size.24}",
          "letterSpacing": "{brk-opt-letter-spacing.2%}",
          "paragraphSpacing": "",
          "textCase": "{brk-opt-text-transform.none}",
          "textDecoration": "{brk-opt-text-decoration.none}"
        },
        "type": "typography",
        "description": " "
      }
    },
    "lg": {
      "pretitle": {
        "value": {
          "fontFamily": "{brk-opt-font-family.webfont}",
          "fontWeight": "{brk-opt-font-weight.700}",
          "lineHeight": "{brk-opt-font-size.32}",
          "fontSize": "{brk-opt-font-size.32}",
          "letterSpacing": "{brk-opt-letter-spacing.-2%}",
          "paragraphSpacing": "",
          "textCase": "{brk-opt-text-transform.none}",
          "textDecoration": "{brk-opt-text-decoration.none}"
        },
        "type": "typography",
        "description": "NOTE : pour le spré-titre de la carte héros, il faut toujours utiliser le token \"font-size\" pour le \"line-height\". Ceci est important surtout pour les cas dans lesquels on n'aura pas de sous-titre, car cela permet de réserver cet espace du côté code. À noter que même si cette option n'est pas disponible dans le menu déroulant, on peut copier et coller l'information d'une caisse à l'autre."
      },
      "image-height": {
        "value": "{brk-card-hero.sm.image-height}*2",
        "type": "sizing",
        "description": " "
      },
      "padding-horizontal": {
        "value": "{brk-opt-spacing.24}",
        "type": "spacing",
        "description": " "
      },
      "padding-vertical": {
        "value": "{brk-opt-spacing.24}",
        "type": "spacing",
        "description": " "
      },
      "heading-margin-vertical": {
        "value": "{brk-opt-spacing.8}",
        "type": "spacing",
        "description": " "
      },
      "content-gap": {
        "value": "{brk-opt-spacing.24}",
        "type": "spacing",
        "description": "NOTE: Séparation minimale entre les textes et le bouton de la carte en format large."
      },
      "heading": {
        "value": {
          "fontFamily": "{brk-opt-font-family.brand-main}",
          "fontWeight": "{brk-opt-font-weight.950}",
          "lineHeight": "{brk-opt-line-height.100%}",
          "fontSize": "{brk-opt-font-size.48}",
          "letterSpacing": "{brk-opt-letter-spacing.-2%}",
          "paragraphSpacing": "",
          "textCase": "{brk-opt-text-transform.none}",
          "textDecoration": "{brk-opt-text-decoration.none}"
        },
        "type": "typography",
        "description": " "
      },
      "body": {
        "value": {
          "fontFamily": "{brk-opt-font-family.webfont}",
          "fontWeight": "{brk-opt-font-weight.400}",
          "lineHeight": "{brk-opt-line-height.100%}",
          "fontSize": "{brk-opt-font-size.32}",
          "letterSpacing": "{brk-opt-letter-spacing.2%}",
          "paragraphSpacing": "",
          "textCase": "{brk-opt-text-transform.none}",
          "textDecoration": "{brk-opt-text-decoration.none}"
        },
        "type": "typography",
        "description": " "
      }
    },
    "border-width": {
      "value": "{brk-opt-border-width.1}",
      "type": "borderWidth",
      "description": " "
    },
    "border-radius": {
      "value": "{brk-opt-border-radius.16}",
      "type": "borderRadius",
      "description": " "
    }
  },
  "brk-card-hero-standard": {
    "box-shadow": {
      "default": {
        "value": "{brk-opt-box-shadow.none}",
        "type": "boxShadow"
      },
      "hover": {
        "value": "{brk-opt-box-shadow.blur-standard}",
        "type": "boxShadow"
      }
    },
    "pretitle-font-color": {
      "value": "{brk-opt-color-neutral.675}",
      "type": "color",
      "description": " "
    },
    "heading-font-color": {
      "value": "{brk-opt-color-neutral.900}",
      "type": "color",
      "description": " "
    },
    "body-font-color": {
      "value": "{brk-opt-color-neutral.900}",
      "type": "color",
      "description": " "
    },
    "background-color": {
      "value": "{brk-opt-color-neutral.0}",
      "type": "color",
      "description": " "
    },
    "border-color": {
      "value": "{brk-opt-color-neutral.100}",
      "type": "color",
      "description": " "
    }
  },
  "brk-card-hero-inverted": {
    "box-shadow": {
      "default": {
        "value": "{brk-opt-box-shadow.none}",
        "type": "boxShadow"
      },
      "hover": {
        "value": "{brk-opt-box-shadow.blur-standard}",
        "type": "boxShadow"
      }
    },
    "pretitle-font-color": {
      "value": "{brk-opt-color-neutral.100}",
      "type": "color",
      "description": " "
    },
    "heading-font-color": {
      "value": "{brk-opt-color-neutral.50}",
      "type": "color",
      "description": " "
    },
    "body-font-color": {
      "value": "{brk-opt-color-neutral.100}",
      "type": "color",
      "description": " "
    },
    "background-color": {
      "value": "{brk-opt-color-neutral.675}",
      "type": "color",
      "description": " "
    },
    "border-color": {
      "value": "{brk-opt-color-neutral.100}",
      "type": "color",
      "description": " "
    }
  },
  "brk-card-secondary-info": {
    "sm": {
      "height": {
        "value": "{brk-opt-sizing.64}",
        "type": "sizing",
        "description": " "
      }
    },
    "md": {
      "height": {
        "value": "{brk-card-secondary-info.sm.height}*1.5",
        "type": "sizing",
        "description": " "
      }
    },
    "lg": {
      "height": {
        "value": "{brk-card-secondary-info.sm.height}*2",
        "type": "sizing",
        "description": " "
      }
    }
  },
  "brk-card-secondary-info-jackpot": {
    "sm": {
      "heading": {
        "value": {
          "fontFamily": "{brk-opt-font-family.brand-main}",
          "fontWeight": "{brk-opt-font-weight.700}",
          "lineHeight": "{brk-opt-line-height.110%}",
          "fontSize": "{brk-opt-font-size.16}",
          "letterSpacing": "{brk-opt-letter-spacing.-2%}",
          "paragraphSpacing": "",
          "textCase": "{brk-opt-text-transform.none}",
          "textDecoration": "{brk-opt-text-decoration.none}"
        },
        "type": "typography",
        "description": " "
      },
      "body": {
        "value": {
          "fontFamily": "{brk-opt-font-family.webfont}",
          "fontWeight": "{brk-opt-font-weight.700}",
          "lineHeight": "{brk-opt-line-height.100%}",
          "fontSize": "{brk-opt-font-size.16}",
          "letterSpacing": "{brk-opt-letter-spacing.2%}",
          "paragraphSpacing": "",
          "textCase": "{brk-opt-text-transform.uppercase}",
          "textDecoration": "{brk-opt-text-decoration.none}"
        },
        "type": "typography",
        "description": " "
      },
      "amount-digit-height": {
        "value": "{brk-opt-size.28}",
        "type": "sizing",
        "description": " "
      },
      "amount-digit-width": {
        "value": "{brk-opt-size.16}",
        "type": "sizing",
        "description": " "
      },
      "padding-horizontal": {
        "value": "{brk-opt-spacing.16}",
        "type": "spacing",
        "description": " "
      },
      "content-gap": {
        "value": "{brk-opt-spacing.16}",
        "type": "spacing",
        "description": "NOTE: Séparation minimale entre les textes et le montant du gros lot en petit format."
      },
      "amount-digit-margin": {
        "value": "{brk-opt-spacing.2}",
        "type": "spacing",
        "description": " "
      },
      "amount-group-margin": {
        "value": "{brk-opt-spacing.4}",
        "type": "spacing",
        "description": " "
      }
    },
    "md": {
      "heading": {
        "value": {
          "fontFamily": "{brk-opt-font-family.brand-main}",
          "fontWeight": "{brk-opt-font-weight.700}",
          "lineHeight": "{brk-opt-line-height.110%}",
          "fontSize": "{brk-opt-font-size.24}",
          "letterSpacing": "{brk-opt-letter-spacing.-2%}",
          "paragraphSpacing": "",
          "textCase": "{brk-opt-text-transform.none}",
          "textDecoration": "{brk-opt-text-decoration.none}"
        },
        "type": "typography",
        "description": " "
      },
      "body": {
        "value": {
          "fontFamily": "{brk-opt-font-family.webfont}",
          "fontWeight": "{brk-opt-font-weight.700}",
          "lineHeight": "{brk-opt-line-height.100%}",
          "fontSize": "{brk-opt-font-size.24}",
          "letterSpacing": "{brk-opt-letter-spacing.2%}",
          "paragraphSpacing": "",
          "textCase": "{brk-opt-text-transform.none}",
          "textDecoration": "{brk-opt-text-decoration.none}"
        },
        "type": "typography",
        "description": " "
      },
      "amount-digit-height": {
        "value": "{brk-opt-size.40}",
        "type": "sizing",
        "description": " "
      },
      "amount-digit-width": {
        "value": "{brk-opt-size.24}",
        "type": "sizing",
        "description": " "
      },
      "padding-horizontal": {
        "value": "{brk-opt-spacing.24}",
        "type": "spacing",
        "description": " "
      },
      "content-gap": {
        "value": "{brk-opt-spacing.24}",
        "type": "spacing",
        "description": "NOTE: Séparation minimale entre les textes et le montant du gros lot en format moyen."
      },
      "amount-digit-margin": {
        "value": "{brk-opt-spacing.4}",
        "type": "spacing",
        "description": " "
      },
      "amount-group-margin": {
        "value": "{brk-opt-spacing.8}",
        "type": "spacing",
        "description": " "
      }
    },
    "lg": {
      "heading": {
        "value": {
          "fontFamily": "{brk-opt-font-family.brand-main}",
          "fontWeight": "{brk-opt-font-weight.700}",
          "lineHeight": "{brk-opt-line-height.110%}",
          "fontSize": "{brk-opt-font-size.32}",
          "letterSpacing": "{brk-opt-letter-spacing.-2%}",
          "paragraphSpacing": "",
          "textCase": "{brk-opt-text-transform.none}",
          "textDecoration": "{brk-opt-text-decoration.none}"
        },
        "type": "typography",
        "description": " "
      },
      "body": {
        "value": {
          "fontFamily": "{brk-opt-font-family.webfont}",
          "fontWeight": "{brk-opt-font-weight.700}",
          "lineHeight": "{brk-opt-line-height.100%}",
          "fontSize": "{brk-opt-font-size.32}",
          "letterSpacing": "{brk-opt-letter-spacing.2%}",
          "paragraphSpacing": "",
          "textCase": "{brk-opt-text-transform.none}",
          "textDecoration": "{brk-opt-text-decoration.none}"
        },
        "type": "typography",
        "description": " "
      },
      "amount-digit-height": {
        "value": "{brk-opt-size.56}",
        "type": "sizing",
        "description": " "
      },
      "amount-digit-width": {
        "value": "{brk-opt-size.32}",
        "type": "sizing",
        "description": " "
      },
      "padding-horizontal": {
        "value": "{brk-opt-spacing.32}",
        "type": "spacing",
        "description": " "
      },
      "content-gap": {
        "value": "{brk-opt-spacing.32}",
        "type": "spacing",
        "description": "NOTE: Séparation minimale entre les textes et le montant du gros lot en format large."
      },
      "amount-digit-margin": {
        "value": "{brk-opt-spacing.8}",
        "type": "spacing",
        "description": " "
      },
      "amount-group-margin": {
        "value": "{brk-opt-spacing.16}",
        "type": "spacing",
        "description": " "
      }
    },
    "amount-digit-border-radius": {
      "value": "{brk-opt-border-radius.2}",
      "type": "borderRadius",
      "description": " "
    },
    "amount-digit-border-width": {
      "value": "{brk-opt-border-width.0}",
      "type": "borderWidth",
      "description": " "
    }
  },
  "brk-card-secondary-info-jackpot-standard": {
    "heading-font-color": {
      "value": "{brk-opt-color-neutral.0}",
      "type": "color",
      "description": " "
    },
    "body-font-color": {
      "value": "{brk-opt-color-neutral.900}",
      "type": "color",
      "description": " "
    },
    "body-box-background-color": {
      "value": "{brk-opt-color-neutral.0}",
      "type": "color",
      "description": " "
    },
    "body-box-border-color": {
      "value": "{brk-opt-color-neutral.transparent}",
      "type": "color",
      "description": " "
    },
    "background-color": {
      "value": "{brk-opt-color-neutral.900}",
      "type": "color",
      "description": " "
    },
    "symbol-font-color": {
      "value": "{brk-opt-color-neutral.0}",
      "type": "color",
      "description": " "
    }
  },
  "brk-card-secondary-info-jackpot-inverted": {
    "heading-font-color": {
      "value": "{brk-opt-color-neutral.900}",
      "type": "color",
      "description": " "
    },
    "body-font-color": {
      "value": "{brk-opt-color-neutral.900}",
      "type": "color",
      "description": " "
    },
    "body-box-background-color": {
      "value": "{brk-opt-color-neutral.0}",
      "type": "color",
      "description": " "
    },
    "body-box-border-color": {
      "value": "{brk-opt-color-neutral.transparent}",
      "type": "color",
      "description": " "
    },
    "background-color": {
      "value": "{brk-opt-color-neutral.100}",
      "type": "color",
      "description": " "
    },
    "symbol-font-color": {
      "value": "{brk-opt-color-neutral.900}",
      "type": "color",
      "description": " "
    }
  },
  "brk-card-secondary-info-logo": {
    "sm": {
      "logo-height": {
        "value": "{brk-opt-sizing.48}",
        "type": "sizing",
        "description": " "
      },
      "padding-horizontal": {
        "value": "{brk-opt-spacing.16}",
        "type": "spacing",
        "description": " "
      }
    },
    "md": {
      "logo-height": {
        "value": "{brk-opt-sizing.72}",
        "type": "sizing",
        "description": " "
      },
      "padding-horizontal": {
        "value": "{brk-opt-spacing.24}",
        "type": "spacing",
        "description": " "
      }
    },
    "lg": {
      "logo-height": {
        "value": "{brk-opt-sizing.96}",
        "type": "sizing",
        "description": " "
      },
      "padding-horizontal": {
        "value": "{brk-opt-spacing.32}",
        "type": "spacing",
        "description": " "
      }
    }
  },
  "brk-card-secondary-info-logo-standard": {
    "background-color": {
      "value": "{brk-opt-color-neutral.900}",
      "type": "color",
      "description": " "
    }
  },
  "brk-card-secondary-info-logo-inverted": {
    "background-color": {
      "value": "{brk-opt-color-neutral.100}",
      "type": "color",
      "description": " "
    }
  },
  "brk-card-secondary-info-text": {
    "sm": {
      "padding-horizontal": {
        "value": "{brk-opt-spacing.16}",
        "type": "spacing",
        "description": " "
      },
      "content-gap": {
        "value": "{brk-opt-spacing.4}",
        "type": "spacing"
      },
      "heading": {
        "value": {
          "fontFamily": "{brk-opt-font-family.brand-main}",
          "fontWeight": "{brk-opt-font-weight.700}",
          "lineHeight": "{brk-opt-line-height.110%}",
          "fontSize": "{brk-opt-font-size.20}",
          "letterSpacing": "{brk-opt-letter-spacing.-2%}",
          "paragraphSpacing": "",
          "textCase": "{brk-opt-text-transform.none}",
          "textDecoration": "{brk-opt-text-decoration.none}"
        },
        "type": "typography",
        "description": " "
      },
      "body": {
        "value": {
          "fontFamily": "{brk-opt-font-family.webfont}",
          "fontWeight": "{brk-opt-font-weight.700}",
          "lineHeight": "{brk-opt-line-height.100%}",
          "fontSize": "{brk-opt-font-size.16}",
          "letterSpacing": "{brk-opt-letter-spacing.0%}",
          "paragraphSpacing": "",
          "textCase": "{brk-opt-text-transform.none}",
          "textDecoration": "{brk-opt-text-decoration.none}"
        },
        "type": "typography",
        "description": " "
      }
    },
    "md": {
      "padding-horizontal": {
        "value": "{brk-opt-spacing.24}",
        "type": "spacing",
        "description": " "
      },
      "content-gap": {
        "value": "{brk-opt-spacing.8}",
        "type": "spacing"
      },
      "heading": {
        "value": {
          "fontFamily": "{brk-opt-font-family.brand-main}",
          "fontWeight": "{brk-opt-font-weight.700}",
          "lineHeight": "{brk-opt-line-height.110%}",
          "fontSize": "{brk-opt-font-size.28}",
          "letterSpacing": "{brk-opt-letter-spacing.-2%}",
          "paragraphSpacing": "",
          "textCase": "{brk-opt-text-transform.none}",
          "textDecoration": "{brk-opt-text-decoration.none}"
        },
        "type": "typography",
        "description": " "
      },
      "body": {
        "value": {
          "fontFamily": "{brk-opt-font-family.webfont}",
          "fontWeight": "{brk-opt-font-weight.700}",
          "lineHeight": "{brk-opt-line-height.100%}",
          "fontSize": "{brk-opt-font-size.24}",
          "letterSpacing": "{brk-opt-letter-spacing.0%}",
          "paragraphSpacing": "",
          "textCase": "{brk-opt-text-transform.none}",
          "textDecoration": "{brk-opt-text-decoration.none}"
        },
        "type": "typography",
        "description": " "
      }
    },
    "lg": {
      "padding-horizontal": {
        "value": "{brk-opt-spacing.32}",
        "type": "spacing",
        "description": " "
      },
      "content-gap": {
        "value": "{brk-opt-spacing.16}",
        "type": "spacing"
      },
      "heading": {
        "value": {
          "fontFamily": "{brk-opt-font-family.brand-main}",
          "fontWeight": "{brk-opt-font-weight.700}",
          "lineHeight": "{brk-opt-line-height.110%}",
          "fontSize": "{brk-opt-font-size.28}",
          "letterSpacing": "{brk-opt-letter-spacing.-2%}",
          "paragraphSpacing": "",
          "textCase": "{brk-opt-text-transform.none}",
          "textDecoration": "{brk-opt-text-decoration.none}"
        },
        "type": "typography",
        "description": " "
      },
      "body": {
        "value": {
          "fontFamily": "{brk-opt-font-family.webfont}",
          "fontWeight": "{brk-opt-font-weight.700}",
          "lineHeight": "{brk-opt-line-height.100%}",
          "fontSize": "{brk-opt-font-size.32}",
          "letterSpacing": "{brk-opt-letter-spacing.0%}",
          "paragraphSpacing": "",
          "textCase": "{brk-opt-text-transform.none}",
          "textDecoration": "{brk-opt-text-decoration.none}"
        },
        "type": "typography",
        "description": " "
      }
    }
  },
  "brk-card-secondary-info-text-standard": {
    "heading-font-color": {
      "value": "{brk-opt-color-neutral.50}",
      "type": "color",
      "description": " "
    },
    "body-font-color": {
      "value": "{brk-opt-color-neutral.100}",
      "type": "color",
      "description": " "
    },
    "background-color": {
      "value": "{brk-opt-color-neutral.900}",
      "type": "color",
      "description": " "
    }
  },
  "brk-card-secondary-info-text-inverted": {
    "heading-font-color": {
      "value": "{brk-opt-color-neutral.900}",
      "type": "color",
      "description": " "
    },
    "body-font-color": {
      "value": "{brk-opt-color-neutral.900}",
      "type": "color",
      "description": " "
    },
    "background-color": {
      "value": "{brk-opt-color-neutral.100}",
      "type": "color",
      "description": " "
    }
  },
  "brk-promo": {
    "secondary-border-radius": {
      "value": "{brk-card-hero.border-radius}",
      "type": "borderRadius",
      "description": " "
    },
    "primary-border-radius": {
      "value": "{brk-opt-border-radius.0}",
      "type": "borderRadius",
      "description": " "
    },
    "tertiary-border-radius": {
      "value": "{brk-opt-border-radius.0}",
      "type": "borderRadius",
      "description": " "
    },
    "tertiary-frame-border-radius": {
      "value": "{brk-card-hero.border-radius}",
      "type": "borderRadius",
      "description": " "
    },
    "primary-frame-border-radius": {
      "value": "{brk-card-hero.border-radius}",
      "type": "borderRadius",
      "description": " "
    },
    "secondary-frame-border-radius": {
      "value": "{brk-card-hero.border-radius}",
      "type": "borderRadius",
      "description": " "
    },
    "primary-border-width": {
      "value": "{brk-card-hero.border-width}",
      "type": "borderWidth",
      "description": " "
    },
    "secondary-border-width": {
      "value": "{brk-card-hero.border-width}",
      "type": "borderWidth",
      "description": " "
    },
    "tertiary-border-width": {
      "value": "{brk-card-hero.border-width}",
      "type": "borderWidth",
      "description": " "
    },
    "primary-content-vertical-align": {
      "value": "{brk-opt-vertical-align.center}",
      "type": "other"
    },
    "secondary-content-vertical-align": {
      "value": "{brk-opt-vertical-align.center}",
      "type": "other"
    },
    "tertiary-content-vertical-align": {
      "value": "{brk-opt-vertical-align.bottom}",
      "type": "other"
    }
  },
  "brk-promo-primary": {
    "sm": {
      "image-height": {
        "value": "{brk-opt-size.245}",
        "type": "sizing",
        "description": " "
      },
      "gradient-height": {
        "value": "{brk-promo-primary.sm.image-height}/4",
        "type": "sizing",
        "description": " "
      },
      "padding-horizontal": {
        "value": "{brk-opt-space.16}",
        "type": "spacing",
        "description": " "
      },
      "padding-vertical": {
        "value": "{brk-opt-space.16}",
        "type": "spacing",
        "description": " "
      },
      "content-gap": {
        "value": "{brk-opt-space.16}",
        "type": "spacing",
        "description": " "
      },
      "pretitle": {
        "value": {
          "fontFamily": "{brk-opt-font-family.webfont}",
          "fontWeight": "{brk-opt-font-weight.700}",
          "lineHeight": "{brk-opt-line-height.110%}",
          "fontSize": "{brk-opt-font-size.13}",
          "letterSpacing": "{brk-opt-letter-spacing.0%}",
          "paragraphSpacing": "",
          "textDecoration": "{brk-opt-text-decoration.none}",
          "textCase": "{brk-opt-text-transform.none}"
        },
        "type": "typography"
      },
      "pretitle-margin-bottom": {
        "value": "{brk-opt-space.6}",
        "type": "spacing",
        "description": " "
      },
      "body-margin-top": {
        "value": "{brk-opt-space.8}",
        "type": "spacing",
        "description": " "
      },
      "heading": {
        "value": {
          "fontFamily": "{brk-opt-font-family.brand-main}",
          "fontWeight": "{brk-opt-font-weight.950}",
          "lineHeight": "{brk-opt-line-height.110%}",
          "fontSize": "{brk-opt-font-size.28}",
          "letterSpacing": "{brk-opt-letter-spacing.-2%}",
          "paragraphSpacing": "",
          "textCase": "{brk-opt-text-transform.none}",
          "textDecoration": "{brk-opt-text-decoration.none}"
        },
        "type": "typography",
        "description": " "
      },
      "body": {
        "value": {
          "fontFamily": "{brk-opt-font-family.webfont}",
          "fontWeight": "{brk-opt-font-weight.400}",
          "lineHeight": "{brk-opt-line-height.120%}",
          "fontSize": "{brk-opt-font-size.16}",
          "letterSpacing": "{brk-opt-letter-spacing.-2%}",
          "paragraphSpacing": "",
          "textDecoration": "{brk-opt-text-decoration.none}",
          "textCase": "{brk-opt-text-transform.none}"
        },
        "type": "typography",
        "description": " "
      }
    },
    "md": {
      "padding-horizontal": {
        "value": "{brk-opt-space.20}",
        "type": "spacing",
        "description": " "
      },
      "padding-vertical": {
        "value": "{brk-opt-space.20}",
        "type": "spacing",
        "description": " "
      },
      "content-gap": {
        "value": "{brk-opt-space.16}",
        "type": "spacing",
        "description": " "
      },
      "pretitle-margin-bottom": {
        "value": "{brk-opt-space.6}",
        "type": "spacing",
        "description": " "
      },
      "body-margin-top": {
        "value": "{brk-opt-space.12}",
        "type": "spacing",
        "description": " "
      },
      "image-height": {
        "value": "{brk-opt-size.270}",
        "type": "sizing",
        "description": " "
      },
      "gradient-height": {
        "value": "{brk-promo-primary.md.image-height}/4",
        "type": "sizing",
        "description": " "
      },
      "pretitle": {
        "value": {
          "fontFamily": "{brk-opt-font-family.webfont}",
          "fontWeight": "{brk-opt-font-weight.700}",
          "lineHeight": "{brk-opt-line-height.110%}",
          "fontSize": "{brk-opt-font-size.14}",
          "letterSpacing": "{brk-opt-letter-spacing.0%}",
          "paragraphSpacing": "",
          "textDecoration": "{brk-opt-text-decoration.none}",
          "textCase": "{brk-opt-text-transform.none}"
        },
        "type": "typography"
      },
      "heading": {
        "value": {
          "fontFamily": "{brk-opt-font-family.brand-main}",
          "fontWeight": "{brk-opt-font-weight.950}",
          "lineHeight": "{brk-opt-line-height.110%}",
          "fontSize": "{brk-opt-font-size.28}",
          "letterSpacing": "{brk-opt-letter-spacing.-2%}",
          "paragraphSpacing": "",
          "textCase": "{brk-opt-text-transform.none}",
          "textDecoration": "{brk-opt-text-decoration.none}"
        },
        "type": "typography",
        "description": " "
      },
      "body": {
        "value": {
          "fontFamily": "{brk-opt-font-family.webfont}",
          "fontWeight": "{brk-opt-font-weight.400}",
          "lineHeight": "{brk-opt-line-height.120%}",
          "fontSize": "{brk-opt-font-size.18}",
          "letterSpacing": "{brk-opt-letter-spacing.-2%}",
          "paragraphSpacing": "",
          "textDecoration": "{brk-opt-text-decoration.none}",
          "textCase": "{brk-opt-text-transform.none}"
        },
        "type": "typography",
        "description": " "
      }
    },
    "lg": {
      "image-height": {
        "value": "{brk-opt-size.300}",
        "type": "sizing",
        "description": " "
      },
      "gradient-height": {
        "value": "{brk-promo-primary.lg.image-height}/4",
        "type": "sizing",
        "description": " "
      },
      "pretitle": {
        "value": {
          "fontFamily": "{brk-opt-font-family.webfont}",
          "fontWeight": "{brk-opt-font-weight.700}",
          "lineHeight": "{brk-opt-line-height.110%}",
          "fontSize": "{brk-opt-font-size.16}",
          "letterSpacing": "{brk-opt-letter-spacing.0%}",
          "paragraphSpacing": "",
          "textDecoration": "{brk-opt-text-decoration.none}",
          "textCase": "{brk-opt-text-transform.none}"
        },
        "type": "typography"
      },
      "heading": {
        "value": {
          "fontFamily": "{brk-opt-font-family.brand-main}",
          "fontWeight": "{brk-opt-font-weight.950}",
          "lineHeight": "{brk-opt-line-height.110%}",
          "fontSize": "{brk-opt-font-size.32}",
          "letterSpacing": "{brk-opt-letter-spacing.-2%}",
          "paragraphSpacing": "",
          "textCase": "{brk-opt-text-transform.none}",
          "textDecoration": "{brk-opt-text-decoration.none}"
        },
        "type": "typography",
        "description": " "
      },
      "body": {
        "value": {
          "fontFamily": "{brk-opt-font-family.webfont}",
          "fontWeight": "{brk-opt-font-weight.400}",
          "lineHeight": "{brk-opt-line-height.120%}",
          "fontSize": "{brk-opt-font-size.20}",
          "letterSpacing": "{brk-opt-letter-spacing.-2%}",
          "paragraphSpacing": "",
          "textDecoration": "{brk-opt-text-decoration.none}",
          "textCase": "{brk-opt-text-transform.none}"
        },
        "type": "typography",
        "description": " "
      },
      "padding-horizontal": {
        "value": "{brk-opt-space.24}",
        "type": "spacing",
        "description": " "
      },
      "padding-vertical": {
        "value": "{brk-opt-space.24}",
        "type": "spacing",
        "description": " "
      },
      "content-gap": {
        "value": "{brk-opt-space.16}",
        "type": "spacing",
        "description": " "
      },
      "pretitle-margin-bottom": {
        "value": "{brk-opt-space.6}",
        "type": "spacing",
        "description": " "
      },
      "body-margin-top": {
        "value": "{brk-opt-space.10}",
        "type": "spacing",
        "description": " "
      }
    }
  },
  "brk-promo-primary-standard": {
    "pretitle-font-color": {
      "value": "{brk-opt-color-neutral.900}",
      "type": "color",
      "description": " "
    },
    "heading-font-color": {
      "value": "{brk-opt-color-neutral.900}",
      "type": "color",
      "description": " "
    },
    "body-font-color": {
      "value": "{brk-opt-color-neutral.900}",
      "type": "color",
      "description": " "
    },
    "background-color": {
      "value": "{brk-opt-color-neutral.0}",
      "type": "color",
      "description": " "
    },
    "border-color": {
      "value": "{brk-opt-color-neutral.100}",
      "type": "color",
      "description": " "
    },
    "gradient-color": {
      "value": "linear-gradient(180deg, {brk-promo-primary-standard.background-color}00 0%, {brk-promo-primary-standard.background-color} 100%)",
      "type": "color",
      "description": " "
    },
    "frame-color": {
      "value": "{brk-opt-color-neutral.transparent}",
      "type": "color",
      "description": " "
    }
  },
  "brk-promo-primary-inverted": {
    "pretitle-font-color": {
      "value": "{brk-opt-color-neutral.0}",
      "type": "color",
      "description": " "
    },
    "heading-font-color": {
      "value": "{brk-opt-color-neutral.0}",
      "type": "color",
      "description": " "
    },
    "body-font-color": {
      "value": "{brk-opt-color-neutral.0}",
      "type": "color",
      "description": " "
    },
    "background-color": {
      "value": "{brk-opt-color-neutral.900}",
      "type": "color",
      "description": " "
    },
    "border-color": {
      "value": "{brk-opt-color-neutral.100}",
      "type": "color",
      "description": " "
    },
    "gradient-color": {
      "value": "linear-gradient(180deg, {brk-promo-primary-inverted.background-color}00 0%, {brk-promo-primary-inverted.background-color} 100%)",
      "type": "color",
      "description": " "
    },
    "frame-color": {
      "value": "{brk-opt-color-neutral.transparent}",
      "type": "color",
      "description": " "
    }
  },
  "brk-promo-secondary": {
    "sm": {
      "image-height": {
        "value": "{brk-opt-size.264}",
        "type": "sizing",
        "description": " "
      },
      "gradient-height": {
        "value": "{brk-promo-secondary.sm.image-height}/4",
        "type": "sizing",
        "description": " "
      },
      "pretitle": {
        "value": {
          "fontFamily": "{brk-opt-font-family.webfont}",
          "fontWeight": "{brk-opt-font-weight.700}",
          "lineHeight": "{brk-opt-line-height.110%}",
          "fontSize": "{brk-opt-font-size.16}",
          "letterSpacing": "{brk-opt-letter-spacing.0%}",
          "paragraphSpacing": "",
          "textDecoration": "{brk-opt-text-decoration.none}",
          "textCase": "{brk-opt-text-transform.none}"
        },
        "type": "typography"
      },
      "heading": {
        "value": {
          "fontFamily": "{brk-opt-font-family.brand-main}",
          "fontWeight": "{brk-opt-font-weight.950}",
          "lineHeight": "{brk-opt-line-height.120%}",
          "fontSize": "{brk-opt-font-size.24}",
          "letterSpacing": "{brk-opt-letter-spacing.-2%}",
          "paragraphSpacing": "",
          "textCase": "{brk-opt-text-transform.none}",
          "textDecoration": "{brk-opt-text-decoration.none}"
        },
        "type": "typography",
        "description": " "
      },
      "padding-horizontal": {
        "value": "{brk-opt-space.16}",
        "type": "spacing",
        "description": " "
      },
      "padding-vertical": {
        "value": "{brk-opt-space.16}",
        "type": "spacing",
        "description": " "
      },
      "content-gap": {
        "value": "{brk-opt-space.16}",
        "type": "spacing",
        "description": " "
      },
      "pretitle-margin-bottom": {
        "value": "{brk-opt-space.4}",
        "type": "spacing",
        "description": " "
      }
    },
    "md": {
      "image-height": {
        "value": "{brk-opt-size.340}",
        "type": "sizing",
        "description": " "
      },
      "gradient-height": {
        "value": "{brk-promo-secondary.md.image-height}/4",
        "type": "sizing",
        "description": " "
      },
      "pretitle": {
        "value": {
          "fontFamily": "{brk-opt-font-family.webfont}",
          "fontWeight": "{brk-opt-font-weight.700}",
          "lineHeight": "{brk-opt-line-height.110%}",
          "fontSize": "{brk-opt-font-size.20}",
          "letterSpacing": "{brk-opt-letter-spacing.0%}",
          "paragraphSpacing": "",
          "textDecoration": "{brk-opt-text-decoration.none}",
          "textCase": "{brk-opt-text-transform.none}"
        },
        "type": "typography"
      },
      "heading": {
        "value": {
          "fontFamily": "{brk-opt-font-family.brand-main}",
          "fontWeight": "{brk-opt-font-weight.950}",
          "lineHeight": "{brk-opt-line-height.110%}",
          "fontSize": "{brk-opt-font-size.36}",
          "letterSpacing": "{brk-opt-letter-spacing.-2%}",
          "paragraphSpacing": "",
          "textCase": "{brk-opt-text-transform.none}",
          "textDecoration": "{brk-opt-text-decoration.none}"
        },
        "type": "typography",
        "description": " "
      },
      "padding-horizontal": {
        "value": "{brk-opt-space.24}",
        "type": "spacing",
        "description": " "
      },
      "padding-vertical": {
        "value": "{brk-opt-space.20}",
        "type": "spacing",
        "description": " "
      },
      "content-gap": {
        "value": "{brk-opt-space.16}",
        "type": "spacing",
        "description": " "
      },
      "pretitle-margin-bottom": {
        "value": "{brk-opt-space.8}",
        "type": "spacing",
        "description": " "
      }
    },
    "lg": {
      "image-height": {
        "value": "{brk-opt-size.340}",
        "type": "sizing",
        "description": " "
      },
      "gradient-height": {
        "value": "{brk-promo-secondary.lg.image-height}/4",
        "type": "sizing",
        "description": " "
      },
      "pretitle": {
        "value": {
          "fontFamily": "{brk-opt-font-family.webfont}",
          "fontWeight": "{brk-opt-font-weight.700}",
          "lineHeight": "{brk-opt-line-height.110%}",
          "fontSize": "{brk-opt-font-size.24}",
          "letterSpacing": "{brk-opt-letter-spacing.0%}",
          "paragraphSpacing": "",
          "textDecoration": "{brk-opt-text-decoration.none}",
          "textCase": "{brk-opt-text-transform.none}"
        },
        "type": "typography"
      },
      "heading": {
        "value": {
          "fontFamily": "{brk-opt-font-family.brand-main}",
          "fontWeight": "{brk-opt-font-weight.950}",
          "lineHeight": "{brk-opt-line-height.110%}",
          "fontSize": "{brk-opt-font-size.48}",
          "letterSpacing": "{brk-opt-letter-spacing.-2%}",
          "paragraphSpacing": "",
          "textCase": "{brk-opt-text-transform.none}",
          "textDecoration": "{brk-opt-text-decoration.none}"
        },
        "type": "typography",
        "description": " "
      },
      "padding-horizontal": {
        "value": "{brk-opt-space.24}",
        "type": "spacing",
        "description": " "
      },
      "padding-vertical": {
        "value": "{brk-opt-space.20}",
        "type": "spacing",
        "description": " "
      },
      "content-gap": {
        "value": "{brk-opt-space.16}",
        "type": "spacing",
        "description": " "
      },
      "pretitle-margin-bottom": {
        "value": "{brk-opt-space.4}",
        "type": "spacing",
        "description": " "
      }
    }
  },
  "brk-promo-secondary-standard": {
    "pretitle-font-color": {
      "value": "{brk-opt-color-neutral.900}",
      "type": "color",
      "description": " "
    },
    "heading-font-color": {
      "value": "{brk-opt-color-neutral.900}",
      "type": "color",
      "description": " "
    },
    "body-font-color": {
      "value": "{brk-opt-color-neutral.900}",
      "type": "color",
      "description": " "
    },
    "background-color": {
      "value": "{brk-opt-color-neutral.0}",
      "type": "color",
      "description": " "
    },
    "border-color": {
      "value": "{brk-opt-color-neutral.100}",
      "type": "color",
      "description": " "
    },
    "gradient-color": {
      "value": "linear-gradient(180deg, {brk-promo-secondary-standard.background-color}00 0%, {brk-promo-secondary-standard.background-color} 100%)",
      "type": "color",
      "description": " "
    },
    "box-shadow": {
      "default": {
        "value": "{brk-opt-box-shadow.none}",
        "type": "boxShadow"
      },
      "hover": {
        "value": "{brk-opt-box-shadow.blur-standard}",
        "type": "boxShadow"
      }
    },
    "frame-color": {
      "value": "{brk-opt-color-neutral.transparent}",
      "type": "color",
      "description": " "
    }
  },
  "brk-promo-secondary-inverted": {
    "pretitle-font-color": {
      "value": "{brk-opt-color-neutral.0}",
      "type": "color",
      "description": " "
    },
    "heading-font-color": {
      "value": "{brk-opt-color-neutral.0}",
      "type": "color",
      "description": " "
    },
    "body-font-color": {
      "value": "{brk-opt-color-neutral.0}",
      "type": "color",
      "description": " "
    },
    "background-color": {
      "value": "{brk-opt-color-neutral.900}",
      "type": "color",
      "description": " "
    },
    "border-color": {
      "value": "{brk-opt-color-neutral.100}",
      "type": "color",
      "description": " "
    },
    "gradient-color": {
      "value": "linear-gradient(180deg, {brk-promo-secondary-inverted.background-color}00 0%, {brk-promo-secondary-inverted.background-color} 100%)",
      "type": "color",
      "description": " "
    },
    "frame-color": {
      "value": "{brk-opt-color-neutral.transparent}",
      "type": "color",
      "description": " "
    }
  },
  "brk-promo-tertiary": {
    "sm": {
      "image-height": {
        "value": "{brk-opt-size.264}",
        "type": "sizing",
        "description": " "
      },
      "gradient-height": {
        "value": "{brk-promo-secondary.sm.image-height}/4",
        "type": "sizing",
        "description": " "
      },
      "padding-horizontal": {
        "value": "{brk-opt-space.16}",
        "type": "spacing",
        "description": " "
      },
      "padding-vertical": {
        "value": "{brk-opt-space.16}",
        "type": "spacing",
        "description": " "
      },
      "frame-padding-horizontal": {
        "value": "{brk-opt-space.16}",
        "type": "spacing",
        "description": " "
      },
      "frame-padding-vertical": {
        "value": "{brk-opt-space.16}",
        "type": "spacing",
        "description": " "
      },
      "content-gap": {
        "value": "{brk-opt-space.16}",
        "type": "spacing",
        "description": " "
      },
      "pretitle-margin-bottom": {
        "value": "{brk-opt-space.4}",
        "type": "spacing",
        "description": " "
      },
      "pretitle": {
        "value": {
          "fontFamily": "{brk-opt-font-family.webfont}",
          "fontWeight": "{brk-opt-font-weight.700}",
          "lineHeight": "{brk-opt-line-height.110%}",
          "fontSize": "{brk-opt-font-size.13}",
          "letterSpacing": "{brk-opt-letter-spacing.0%}",
          "paragraphSpacing": "",
          "textDecoration": "{brk-opt-text-decoration.none}",
          "textCase": "{brk-opt-text-transform.none}"
        },
        "type": "typography"
      },
      "heading": {
        "value": {
          "fontFamily": "{brk-opt-font-family.brand-main}",
          "fontWeight": "{brk-opt-font-weight.950}",
          "lineHeight": "{brk-opt-line-height.110%}",
          "fontSize": "{brk-opt-font-size.28}",
          "letterSpacing": "{brk-opt-letter-spacing.-2%}",
          "paragraphSpacing": "",
          "textCase": "{brk-opt-text-transform.none}",
          "textDecoration": "{brk-opt-text-decoration.none}"
        },
        "type": "typography",
        "description": " "
      }
    },
    "md": {
      "image-height": {
        "value": "{brk-opt-size.270}",
        "type": "sizing",
        "description": " "
      },
      "gradient-height": {
        "value": "{brk-promo-secondary.md.image-height}/4",
        "type": "sizing",
        "description": " "
      },
      "padding-horizontal": {
        "value": "{brk-opt-space.20}",
        "type": "spacing",
        "description": " "
      },
      "padding-vertical": {
        "value": "{brk-opt-space.20}",
        "type": "spacing",
        "description": " "
      },
      "frame-padding-horizontal": {
        "value": "{brk-opt-space.20}",
        "type": "spacing",
        "description": " "
      },
      "frame-padding-vertical": {
        "value": "{brk-opt-space.20}",
        "type": "spacing",
        "description": " "
      },
      "content-gap": {
        "value": "{brk-opt-space.16}",
        "type": "spacing",
        "description": " "
      },
      "pretitle-margin-bottom": {
        "value": "{brk-opt-space.6}",
        "type": "spacing",
        "description": " "
      },
      "pretitle": {
        "value": {
          "fontFamily": "{brk-opt-font-family.webfont}",
          "fontWeight": "{brk-opt-font-weight.700}",
          "lineHeight": "{brk-opt-line-height.110%}",
          "fontSize": "{brk-opt-font-size.14}",
          "letterSpacing": "{brk-opt-letter-spacing.0%}",
          "paragraphSpacing": "",
          "textDecoration": "{brk-opt-text-decoration.none}",
          "textCase": "{brk-opt-text-transform.none}"
        },
        "type": "typography"
      },
      "heading": {
        "value": {
          "fontFamily": "{brk-opt-font-family.brand-main}",
          "fontWeight": "{brk-opt-font-weight.950}",
          "lineHeight": "{brk-opt-line-height.110%}",
          "fontSize": "{brk-opt-font-size.28}",
          "letterSpacing": "{brk-opt-letter-spacing.-2%}",
          "paragraphSpacing": "",
          "textCase": "{brk-opt-text-transform.none}",
          "textDecoration": "{brk-opt-text-decoration.none}"
        },
        "type": "typography",
        "description": " "
      }
    },
    "lg": {
      "image-height": {
        "value": "{brk-opt-size.300}",
        "type": "sizing",
        "description": " "
      },
      "gradient-height": {
        "value": "{brk-promo-secondary.lg.image-height}/4",
        "type": "sizing",
        "description": " "
      },
      "padding-horizontal": {
        "value": "{brk-opt-space.24}",
        "type": "spacing",
        "description": " "
      },
      "padding-vertical": {
        "value": "{brk-opt-space.24}",
        "type": "spacing",
        "description": " "
      },
      "frame-padding-horizontal": {
        "value": "{brk-opt-space.20}",
        "type": "spacing",
        "description": " "
      },
      "frame-padding-vertical": {
        "value": "{brk-opt-space.20}",
        "type": "spacing",
        "description": " "
      },
      "content-gap": {
        "value": "{brk-opt-space.16}",
        "type": "spacing",
        "description": " "
      },
      "pretitle-margin-bottom": {
        "value": "{brk-opt-space.6}",
        "type": "spacing",
        "description": " "
      },
      "pretitle": {
        "value": {
          "fontFamily": "{brk-opt-font-family.webfont}",
          "fontWeight": "{brk-opt-font-weight.700}",
          "lineHeight": "{brk-opt-line-height.110%}",
          "fontSize": "{brk-opt-font-size.16}",
          "letterSpacing": "{brk-opt-letter-spacing.0%}",
          "paragraphSpacing": "",
          "textDecoration": "{brk-opt-text-decoration.none}",
          "textCase": "{brk-opt-text-transform.none}"
        },
        "type": "typography"
      },
      "heading": {
        "value": {
          "fontFamily": "{brk-opt-font-family.brand-main}",
          "fontWeight": "{brk-opt-font-weight.950}",
          "lineHeight": "{brk-opt-line-height.110%}",
          "fontSize": "{brk-opt-font-size.32}",
          "letterSpacing": "{brk-opt-letter-spacing.-2%}",
          "paragraphSpacing": "",
          "textCase": "{brk-opt-text-transform.none}",
          "textDecoration": "{brk-opt-text-decoration.none}"
        },
        "type": "typography",
        "description": " "
      }
    }
  },
  "brk-promo-tertiary-standard": {
    "pretitle-font-color": {
      "value": "{brk-opt-color-neutral.900}",
      "type": "color",
      "description": " "
    },
    "heading-font-color": {
      "value": "{brk-opt-color-neutral.900}",
      "type": "color",
      "description": " "
    },
    "body-font-color": {
      "value": "{brk-opt-color-neutral.900}",
      "type": "color",
      "description": " "
    },
    "background-color": {
      "value": "{brk-opt-color-neutral.900}",
      "type": "color",
      "description": " "
    },
    "border-color": {
      "value": "{brk-opt-color-neutral.100}",
      "type": "color",
      "description": " "
    },
    "gradient-color": {
      "value": "linear-gradient(180deg, {brk-promo-tertiary-standard.background-color}00 0%, {brk-promo-tertiary-standard.background-color} 100%)",
      "type": "color",
      "description": " "
    },
    "frame-color": {
      "value": "{brk-opt-color-neutral.0}",
      "type": "color",
      "description": " "
    }
  },
  "brk-promo-tertiary-inverted": {
    "pretitle-font-color": {
      "value": "{brk-opt-color-neutral.0}",
      "type": "color",
      "description": " "
    },
    "heading-font-color": {
      "value": "{brk-opt-color-neutral.0}",
      "type": "color",
      "description": " "
    },
    "body-font-color": {
      "value": "{brk-opt-color-neutral.0}",
      "type": "color",
      "description": " "
    },
    "background-color": {
      "value": "{brk-opt-color-neutral.0}",
      "type": "color",
      "description": " "
    },
    "border-color": {
      "value": "{brk-opt-color-neutral.100}",
      "type": "color",
      "description": " "
    },
    "gradient-color": {
      "value": "linear-gradient(180deg, {brk-promo-tertiary-inverted.background-color}00 0%, {brk-promo-tertiary-inverted.background-color} 100%)",
      "type": "color",
      "description": " "
    },
    "frame-color": {
      "value": "{brk-opt-color-neutral.900}",
      "type": "color",
      "description": " "
    }
  },
  "brk-card-high-density": {
    "sm": {
      "image-height": {
        "value": "{brk-opt-size.42}",
        "type": "sizing"
      },
      "card-height": {
        "value": "{brk-opt-size.50}",
        "type": "sizing"
      },
      "content-gap": {
        "value": "{brk-opt-space.8}",
        "type": "spacing"
      },
      "image-border-radius": {
        "value": "{brk-opt-border-radius.10}",
        "type": "borderRadius"
      },
      "heading": {
        "value": {
          "fontFamily": "{brk-opt-font-family.brand-main}",
          "fontWeight": "{brk-opt-font-weight.700}",
          "lineHeight": "{brk-opt-line-height.110%}",
          "fontSize": "{brk-opt-font-size.10}",
          "letterSpacing": "{brk-opt-letter-spacing.-2%}",
          "paragraphSpacing": "{brk-opt-paragraph-spacing.80%}",
          "textDecoration": "{brk-opt-text-decoration.none}",
          "textCase": "{brk-opt-text-transform.none}"
        },
        "type": "typography"
      },
      "subtitle": {
        "value": {
          "fontFamily": "{brk-opt-font-family.brand-main}",
          "fontWeight": "{brk-opt-font-weight.700}",
          "lineHeight": "{brk-opt-line-height.100%}",
          "fontSize": "{brk-opt-font-size.11}",
          "letterSpacing": "{brk-opt-letter-spacing.-2%}",
          "paragraphSpacing": "{brk-opt-paragraph-spacing.80%}",
          "textDecoration": "{brk-opt-text-decoration.none}",
          "textCase": "{brk-opt-text-transform.none}"
        },
        "type": "typography"
      },
      "body": {
        "value": {
          "fontFamily": "{brk-opt-font-family.webfont}",
          "fontWeight": "{brk-opt-font-weight.400}",
          "lineHeight": "{brk-opt-line-height.100%}",
          "fontSize": "{brk-opt-font-size.10}",
          "letterSpacing": "{brk-opt-letter-spacing.0%}",
          "paragraphSpacing": "{brk-opt-paragraph-spacing.80%}",
          "textDecoration": "{brk-opt-text-decoration.none}",
          "textCase": "{brk-opt-text-transform.none}"
        },
        "type": "typography"
      },
      "heading-margin-bottom": {
        "value": "{brk-opt-space.3}",
        "type": "spacing"
      },
      "subtitle-margin-bottom": {
        "value": "{brk-opt-space.3}",
        "type": "spacing"
      }
    },
    "md": {
      "image-height": {
        "value": "{brk-opt-size.80}",
        "type": "sizing"
      },
      "card-height": {
        "value": "{brk-opt-size.80}",
        "type": "sizing"
      },
      "content-gap": {
        "value": "{brk-opt-space.20}",
        "type": "spacing"
      },
      "image-border-radius": {
        "value": "{brk-opt-border-radius.20}",
        "type": "borderRadius"
      },
      "heading": {
        "value": {
          "fontFamily": "{brk-opt-font-family.brand-main}",
          "fontWeight": "{brk-opt-font-weight.700}",
          "lineHeight": "{brk-opt-line-height.110%}",
          "fontSize": "{brk-opt-font-size.20}",
          "letterSpacing": "{brk-opt-letter-spacing.-2%}",
          "paragraphSpacing": "{brk-opt-paragraph-spacing.80%}",
          "textDecoration": "{brk-opt-text-decoration.none}",
          "textCase": "{brk-opt-text-transform.none}"
        },
        "type": "typography"
      },
      "subtitle": {
        "value": {
          "fontFamily": "{brk-opt-font-family.brand-main}",
          "fontWeight": "{brk-opt-font-weight.700}",
          "lineHeight": "{brk-opt-line-height.100%}",
          "fontSize": "{brk-opt-font-size.16}",
          "letterSpacing": "{brk-opt-letter-spacing.-2%}",
          "paragraphSpacing": "{brk-opt-paragraph-spacing.80%}",
          "textDecoration": "{brk-opt-text-decoration.none}",
          "textCase": "{brk-opt-text-transform.none}"
        },
        "type": "typography"
      },
      "body": {
        "value": {
          "fontFamily": "{brk-opt-font-family.webfont}",
          "fontWeight": "{brk-opt-font-weight.400}",
          "lineHeight": "{brk-opt-line-height.100%}",
          "fontSize": "{brk-opt-font-size.13}",
          "letterSpacing": "{brk-opt-letter-spacing.0%}",
          "paragraphSpacing": "{brk-opt-paragraph-spacing.80%}",
          "textDecoration": "{brk-opt-text-decoration.none}",
          "textCase": "{brk-opt-text-transform.none}"
        },
        "type": "typography"
      },
      "heading-margin-bottom": {
        "value": "{brk-opt-space.3}",
        "type": "spacing"
      },
      "subtitle-margin-bottom": {
        "value": "{brk-opt-space.3}",
        "type": "spacing"
      }
    },
    "lg": {
      "image-height": {
        "value": "{brk-opt-size.90}",
        "type": "sizing"
      },
      "card-height": {
        "value": "{brk-opt-size.90}",
        "type": "sizing"
      },
      "content-gap": {
        "value": "{brk-opt-space.25}",
        "type": "spacing"
      },
      "image-border-radius": {
        "value": "{brk-opt-border-radius.25}",
        "type": "borderRadius"
      },
      "heading": {
        "value": {
          "fontFamily": "{brk-opt-font-family.brand-main}",
          "fontWeight": "{brk-opt-font-weight.700}",
          "lineHeight": "{brk-opt-line-height.110%}",
          "fontSize": "{brk-opt-font-size.22}",
          "letterSpacing": "{brk-opt-letter-spacing.-2%}",
          "paragraphSpacing": "{brk-opt-paragraph-spacing.80%}",
          "textDecoration": "{brk-opt-text-decoration.none}",
          "textCase": "{brk-opt-text-transform.none}"
        },
        "type": "typography"
      },
      "subtitle": {
        "value": {
          "fontFamily": "{brk-opt-font-family.brand-main}",
          "fontWeight": "{brk-opt-font-weight.700}",
          "lineHeight": "{brk-opt-line-height.100%}",
          "fontSize": "{brk-opt-font-size.20}",
          "letterSpacing": "{brk-opt-letter-spacing.-2%}",
          "paragraphSpacing": "{brk-opt-paragraph-spacing.80%}",
          "textDecoration": "{brk-opt-text-decoration.none}",
          "textCase": "{brk-opt-text-transform.none}"
        },
        "type": "typography"
      },
      "body": {
        "value": {
          "fontFamily": "{brk-opt-font-family.webfont}",
          "fontWeight": "{brk-opt-font-weight.400}",
          "lineHeight": "{brk-opt-line-height.100%}",
          "fontSize": "{brk-opt-font-size.16}",
          "letterSpacing": "{brk-opt-letter-spacing.0%}",
          "paragraphSpacing": "{brk-opt-paragraph-spacing.80%}",
          "textDecoration": "{brk-opt-text-decoration.none}",
          "textCase": "{brk-opt-text-transform.none}"
        },
        "type": "typography"
      },
      "heading-margin-bottom": {
        "value": "{brk-opt-space.3}",
        "type": "spacing"
      },
      "subtitle-margin-bottom": {
        "value": "{brk-opt-space.3}",
        "type": "spacing"
      }
    }
  },
  "brk-card-high-density-standard": {
    "heading-font-color": {
      "value": "{brk-opt-color-neutral.900}",
      "type": "color"
    },
    "subtitle-font-color": {
      "value": "#285EB1",
      "type": "color"
    },
    "body-font-color": {
      "value": "{brk-opt-color-neutral.900}",
      "type": "color"
    }
  },
  "brk-card-high-density-inverted": {
    "heading-font-color": {
      "value": "{brk-opt-color-neutral.900}",
      "type": "color"
    },
    "subtitle-font-color": {
      "value": "#285EB1",
      "type": "color"
    },
    "body-font-color": {
      "value": "{brk-opt-color-neutral.900}",
      "type": "color"
    }
  },
  "brk-card-high-density-list": {
    "border-radius": {
      "value": "{brk-opt-border-radius.16}",
      "type": "borderRadius"
    },
    "border-width": {
      "value": "{brk-opt-border-width.1}",
      "type": "borderWidth"
    },
    "sm": {
      "padding-vertical": {
        "value": "{brk-opt-space.15}",
        "type": "spacing"
      },
      "padding-horizontal": {
        "value": "{brk-opt-space.15}",
        "type": "spacing"
      },
      "separator-padding-left": {
        "value": "{brk-opt-space.50}",
        "type": "spacing"
      },
      "separator-padding-vertical": {
        "value": "{brk-opt-space.10}",
        "type": "spacing"
      }
    },
    "md": {
      "padding-vertical": {
        "value": "{brk-opt-space.20}",
        "type": "spacing"
      },
      "padding-horizontal": {
        "value": "{brk-opt-space.20}",
        "type": "spacing"
      },
      "separator-padding-left": {
        "value": "{brk-opt-space.100}",
        "type": "spacing"
      },
      "separator-padding-vertical": {
        "value": "{brk-opt-space.14}",
        "type": "spacing"
      }
    },
    "lg": {
      "padding-vertical": {
        "value": "{brk-opt-space.20}",
        "type": "spacing"
      },
      "padding-horizontal": {
        "value": "{brk-opt-space.25}",
        "type": "spacing"
      },
      "separator-padding-left": {
        "value": "{brk-opt-space.115}",
        "type": "spacing"
      },
      "separator-padding-vertical": {
        "value": "{brk-opt-space.15}",
        "type": "spacing"
      }
    },
    "separator-width": {
      "value": "{brk-opt-border-width.1}",
      "type": "borderWidth"
    }
  },
  "brk-card-high-density-list-standard": {
    "background-color": {
      "value": "{brk-opt-color-neutral.0}",
      "type": "color"
    },
    "border-color": {
      "value": "{brk-opt-color-neutral.100}",
      "type": "color"
    },
    "separator-color": {
      "value": "{brk-opt-color-neutral.100}",
      "type": "color"
    },
    "box-shadow": {
      "default": {
        "value": "{brk-opt-box-shadow.none}",
        "type": "boxShadow"
      },
      "hover": {
        "value": "{brk-opt-box-shadow.blur-standard}",
        "type": "boxShadow"
      }
    }
  },
  "brk-card-high-density-list-inverted": {
    "background-color": {
      "value": "{brk-opt-color-neutral.0}",
      "type": "color"
    },
    "border-color": {
      "value": "{brk-opt-color-neutral.100}",
      "type": "color"
    },
    "separator-color": {
      "value": "{brk-opt-color-neutral.100}",
      "type": "color"
    },
    "box-shadow": {
      "default": {
        "value": "{brk-opt-box-shadow.none}",
        "type": "boxShadow"
      },
      "hover": {
        "value": "{brk-opt-box-shadow.blur-standard}",
        "type": "boxShadow"
      }
    }
  }
}